{
  "backend": [
    {
      "name": "statevector_sim_aer",
      "vendor": "ibm",
      "type": "simulator",
      "noise": false,
      "nshots": 0,
      "_source": "harvester"
    }
  ],
  "results": [
    {
      "_source": "harvester"
    }
  ],
  "analysis": [
    {
      "study_type": "circuit_scaling",
      "mesh": "2x2",
      "grid_points": 4,
      "_source": "harvester"
    }
  ],
  "experiment": [
    {
      "name": "frontier-qlsa-0bbb27f2",
      "experiment_id": "9051a503",
      "workflow_id": "0bbb27f2",
      "timestamp": "2026-03-09T01:52:42.016840Z",
      "user": {
        "username": "agallojr",
        "hostname": "MH-DT9TLJQR2V"
      },
      "_source": "solver"
    }
  ],
  "case": [
    {
      "case_id": "scaling_2x2",
      "nx": 2,
      "ny": 2,
      "NQ_MATRIX": null,
      "matrix_size_original": 4,
      "matrix_size_hermitian": 4,
      "condition_number_original": 1.0,
      "condition_number_hermitian": 1.0,
      "name": "hele-shaw",
      "_source": "harvester",
      "study_type": "circuit_scaling"
    }
  ],
  "exec_stats": [],
  "code": [
    {
      "algorithm": "hhl",
      "entry_point": "circuit_HHL.py",
      "run_args": {
        "study": "scaling",
        "mesh": "2x2"
      },
      "_source": "harvester"
    }
  ],
  "artifacts": [
    {
      "transpile_passes": [
        {
          "step": 0,
          "wall_time_generate_s": 10.670725,
          "before": {
            "depth": 0,
            "num_qubits": 0,
            "gate_count": 0
          },
          "after": {
            "depth": 953,
            "num_qubits": 0,
            "gate_count": 1263
          }
        }
      ],
      "circuit_timing_total_s": {
        "generate": 10.670725,
        "transpile": 0.0,
        "execute": 0.0,
        "total": 10.670725
      },
      "linear_system": {
        "matrix_size_original": 4,
        "matrix_size_hermitian": 4,
        "condition_number_range": [
          1.0,
          1.0
        ]
      },
      "_source": "harvester"
    }
  ]
}