{
  "exec_stats": [
    {
      "_source": "sweep",
      "start_time": "2026-06-03T18:33:04.415416Z",
      "end_time": "2026-06-03T18:33:08.490736Z",
      "duration_seconds": 4.075334,
      "exit_code": 0,
      "success": true
    }
  ],
  "case": [
    {
      "q": 5,
      "N": 32,
      "nu": 0.0001,
      "dx": 0.03125,
      "dt": 0.003125,
      "cfl": 0.1,
      "n_steps": 51,
      "shock_pct": 100.0,
      "ic": "sine",
      "ic_modes": null,
      "ic_seed": null,
      "ic_alpha": null,
      "ic_center": null,
      "ic_sigma": null,
      "ic_cole_hopf_coeffs": null,
      "classical_reference": true,
      "analytic_reference": null,
      "source": "sine",
      "method": "tebd",
      "trotter_order": 1,
      "trotter_reps": 1,
      "bond_dim": null,
      "mps_threshold": 0.0,
      "shots": 0,
      "backend_name": null,
      "t1": null,
      "t2": null,
      "bc": "periodic",
      "sign_recovery": "none",
      "backend_type": "sim",
      "coupling_map": "default",
      "optimization_level": 1,
      "seed": null,
      "name": "burgers_1d",
      "_source": "solver"
    },
    {
      "_source": "sweep",
      "name": "tebd_q5",
      "case_id": "tebd_q5",
      "params": {
        "_output_dir": "/lustre/orion/ard189/scratch/ishangore/burgers_quantum",
        "_inject_outdir": "--outdir",
        "_env": "./q8020-mps-burgers/.venv",
        "_script": "python ./q8020-mps-burgers/src/burgers_solver.py",
        "_slurm": true,
        "_slurm_project": "ard189",
        "_slurm_pack_venvs": [
          "./q8020-mps-burgers/.venv"
        ],
        "_slurm_partition": "extended",
        "_slurm_walltime": "24:00:00",
        "_slurm_cores_per_task": 1,
        "_slurm_cores_per_node": 64,
        "_slurm_exclusive_node": false,
        "_run_mode": "parallel",
        "_trials": 1,
        "_case_timeout": 82800,
        "--noshow": true,
        "--nu": 0.0001,
        "--cfl": 0.1,
        "--ic": "sine",
        "--source": "sine",
        "--q": 5,
        "--shock-pct": 100.0,
        "--method": "tebd",
        "--bc": "periodic",
        "--save-every": 8
      },
      "command": [
        "bash",
        "-c",
        "source /mnt/bb/ishangore/venv_0/bin/activate && python ./q8020-mps-burgers/src/burgers_solver.py --noshow --nu 0.0001 --cfl 0.1 --ic sine --source sine --q 5 --shock-pct 100.0 --method tebd --bc periodic --save-every 8 --outdir /lustre/orion/ard189/scratch/ishangore/burgers_quantum/2026-06-03/_b56add80/64fce4fa"
      ],
      "script": "-c",
      "cwd": "/autofs/nccs-svm1_home1/ishangore/q8020"
    }
  ],
  "results": [
    {
      "u_initial": [
        0.0,
        0.19509032201612825,
        0.3826834323650898,
        0.5555702330196022,
        0.7071067811865475,
        0.8314696123025452,
        0.9238795325112867,
        0.9807852804032304,
        1.0,
        0.9807852804032304,
        0.9238795325112867,
        0.8314696123025455,
        0.7071067811865476,
        0.5555702330196022,
        0.3826834323650899,
        0.1950903220161286,
        1.2246467991473532e-16,
        -0.19509032201612836,
        -0.38268343236508967,
        -0.555570233019602,
        -0.7071067811865475,
        -0.8314696123025452,
        -0.9238795325112865,
        -0.9807852804032303,
        -1.0,
        -0.9807852804032304,
        -0.9238795325112866,
        -0.8314696123025455,
        -0.7071067811865477,
        -0.5555702330196022,
        -0.3826834323650904,
        -0.19509032201612872
      ],
      "u_final_classical": [
        -3.13639208727247e-18,
        0.11165064709497752,
        0.22262608802551326,
        0.33223998159129353,
        0.4397818544198031,
        0.5445000143634676,
        0.6455772890969604,
        0.7420948179477902,
        0.8329759036580083,
        0.9168977120010858,
        0.9921191880049278,
        1.0562164205724627,
        1.1070451378691504,
        1.1285705332659244,
        1.122640016079618,
        1.3160472809064512,
        1.4781869421940482e-15,
        -1.316047280906452,
        -1.1226400160796173,
        -1.1285705332659248,
        -1.1070451378691504,
        -1.0562164205724625,
        -0.9921191880049278,
        -0.9168977120010858,
        -0.8329759036580087,
        -0.7420948179477903,
        -0.6455772890969605,
        -0.5445000143634677,
        -0.43978185441980316,
        -0.3322399815912938,
        -0.22262608802551376,
        -0.11165064709497767
      ],
      "u_final_method": [
        -4.63384929976199e-09,
        0.11165212724196176,
        0.2226289214813243,
        0.33224430240658376,
        0.4397875665565991,
        0.5445069403005874,
        0.645585394068427,
        0.7421036019613344,
        0.8329853937330696,
        0.9169074984520429,
        0.9921294305200976,
        1.0562252654358275,
        1.107051911417914,
        1.1285746527498155,
        1.1226522619850585,
        1.3159616240027303,
        8.162903846198462e-07,
        -1.3159627864707188,
        -1.1226516390571941,
        -1.1285751615988404,
        -1.1070511713620226,
        -1.056225988765944,
        -0.9921289797588261,
        -0.9169076505575733,
        -0.8329853010440318,
        -0.7421037565095551,
        -0.6455852896282551,
        -0.5445070240715403,
        -0.4397875124404067,
        -0.33224427179998955,
        -0.22262900645991593,
        -0.11165203011867346
      ],
      "errors_by_step": {
        "0": 0.0,
        "8": 1.245231919579412e-06,
        "16": 2.546928125409515e-06,
        "24": 4.093429831901393e-06,
        "32": 6.2223252004416265e-06,
        "40": 1.00116126244369e-05,
        "48": 1.9934728084177613e-05,
        "51": 2.7385211849251394e-05
      },
      "final_error": 2.7385211849251394e-05,
      "max_error": 2.7385211849251394e-05,
      "_source": "solver"
    },
    {
      "_source": "stdout",
      "experiment_id": null,
      "algorithm": "burgers_tebd",
      "q": 5,
      "N": 32,
      "nu": 0.0001,
      "n_steps": 51,
      "shock_pct": 100.0,
      "ic": "sine",
      "ic_modes": null,
      "ic_seed": null,
      "ic_alpha": null,
      "ic_center": null,
      "ic_sigma": null,
      "ic_cole_hopf_coeffs": null,
      "classical_reference": true,
      "analytic_reference": null,
      "method": "tebd",
      "bc": "periodic",
      "trotter_order": 1,
      "trotter_reps": 1,
      "shots": 0,
      "t1": null,
      "t2": null,
      "backend_name": null,
      "final_error": 2.7385211849251394e-05,
      "max_error": 2.7385211849251394e-05,
      "classical_time_s": 0.0021963119506835938,
      "method_time_s": 0.31682348251342773,
      "exit_code": 0
    }
  ],
  "artifacts": [
    {
      "_source": "sweep",
      "directory": "/lustre/orion/ard189/scratch/ishangore/burgers_quantum/2026-06-03/_b56add80/64fce4fa",
      "files": [
        {
          "name": "q8020_params_64fce4fa.json",
          "path": "q8020_params_64fce4fa.json",
          "size_bytes": 1095,
          "modified": "2026-06-03T18:33:04Z",
          "type": "json"
        },
        {
          "name": "q8020_analysis_0.json",
          "path": "q8020_analysis_0.json",
          "size_bytes": 17493,
          "modified": "2026-06-03T18:33:08Z",
          "type": "json"
        },
        {
          "name": "q8020_artifacts_0.json",
          "path": "q8020_artifacts_0.json",
          "size_bytes": 7387,
          "modified": "2026-06-03T18:33:08Z",
          "type": "json"
        },
        {
          "name": "q8020_case_0.json",
          "path": "q8020_case_0.json",
          "size_bytes": 719,
          "modified": "2026-06-03T18:33:07Z",
          "type": "json"
        },
        {
          "name": "q8020_stdout_64fce4fa.txt",
          "path": "q8020_stdout_64fce4fa.txt",
          "size_bytes": 675,
          "modified": "2026-06-03T18:33:08Z",
          "type": "txt"
        },
        {
          "name": "q8020_results_0.json",
          "path": "q8020_results_0.json",
          "size_bytes": 2783,
          "modified": "2026-06-03T18:33:07Z",
          "type": "json"
        },
        {
          "name": "q8020_stderr_64fce4fa.txt",
          "path": "q8020_stderr_64fce4fa.txt",
          "size_bytes": 268,
          "modified": "2026-06-03T18:33:07Z",
          "type": "txt"
        },
        {
          "name": "pipeline_args.json",
          "path": "pipeline_args.json",
          "size_bytes": 1539,
          "modified": "2026-06-03T18:32:37Z",
          "type": "json"
        },
        {
          "name": "q8020_env_before_64fce4fa.json",
          "path": "q8020_env_before_64fce4fa.json",
          "size_bytes": 2662,
          "modified": "2026-06-03T18:33:04Z",
          "type": "json"
        }
      ]
    },
    {
      "grid": [
        0.0,
        0.03125,
        0.0625,
        0.09375,
        0.125,
        0.15625,
        0.1875,
        0.21875,
        0.25,
        0.28125,
        0.3125,
        0.34375,
        0.375,
        0.40625,
        0.4375,
        0.46875,
        0.5,
        0.53125,
        0.5625,
        0.59375,
        0.625,
        0.65625,
        0.6875,
        0.71875,
        0.75,
        0.78125,
        0.8125,
        0.84375,
        0.875,
        0.90625,
        0.9375,
        0.96875
      ],
      "solution_steps": {
        "0": [
          0.0,
          0.19509032201612825,
          0.3826834323650898,
          0.5555702330196022,
          0.7071067811865475,
          0.8314696123025452,
          0.9238795325112867,
          0.9807852804032304,
          1.0,
          0.9807852804032304,
          0.9238795325112867,
          0.8314696123025455,
          0.7071067811865476,
          0.5555702330196022,
          0.3826834323650899,
          0.1950903220161286,
          1.2246467991473532e-16,
          -0.19509032201612836,
          -0.38268343236508967,
          -0.555570233019602,
          -0.7071067811865475,
          -0.8314696123025452,
          -0.9238795325112865,
          -0.9807852804032303,
          -1.0,
          -0.9807852804032304,
          -0.9238795325112866,
          -0.8314696123025455,
          -0.7071067811865477,
          -0.5555702330196022,
          -0.3826834323650904,
          -0.19509032201612872
        ],
        "8": [
          -7.468278448506982e-09,
          0.17298965752169002,
          0.34172952418447655,
          0.5019085769923296,
          0.6490984027720396,
          0.7787171623473553,
          0.886019176985223,
          0.9661390875430281,
          1.0142169549211444,
          1.0256467484018246,
          0.9964894290011138,
          0.9240705557486955,
          0.8077471104654571,
          0.6497206886606559,
          0.45567864152807175,
          0.23495797609192895,
          9.039060093764285e-08,
          -0.2349582307140869,
          -0.4556782037208449,
          -0.6497209982587276,
          -0.8077470822236734,
          -0.9240705935942661,
          -0.9964892281285846,
          -1.0256469162293136,
          -1.0142168325828533,
          -0.9661390955949261,
          -0.8860191647744738,
          -0.7787171312657867,
          -0.6490985425517662,
          -0.5019084131233877,
          -0.3417296758894491,
          -0.1729895330970598
        ],
        "16": [
          -9.176876674667591e-09,
          0.1560931445708516,
          0.30957508173960524,
          0.4577460471899567,
          0.5977205798183239,
          0.7263211200482727,
          0.839948628718563,
          0.9344310536276746,
          1.004849148790996,
          1.0453611149948643,
          1.0490993727640399,
          1.0083073552958022,
          0.9150930411818509,
          0.763360774768917,
          0.5523411860332222,
          0.29093475656006534,
          1.0803477732471991e-07,
          -0.2909350269749683,
          -0.5523407034785919,
          -0.7633612344141459,
          -0.9150928843999137,
          -1.0083073599992576,
          -1.0490992257188636,
          -1.0453612978877402,
          -1.0048489687690836,
          -0.934431119742938,
          -0.8399485874335196,
          -0.7263211442989638,
          -0.5977206687592116,
          -0.45774589627442364,
          -0.3095752360426133,
          -0.1560930164388512
        ],
        "24": [
          -7.787643169021486e-09,
          0.14272517931233844,
          0.2837185403684581,
          0.42118413631994994,
          0.5531880485414883,
          0.6775706876618341,
          0.7918268197382646,
          0.8929380118886053,
          0.9771264246129105,
          1.0394792383145475,
          1.0733729886060996,
          1.0695844370945526,
          1.015069271049272,
          0.8920798838879057,
          0.681024244823911,
          0.3742918000608882,
          1.37972303250072e-07,
          -0.37429210214537634,
          -0.6810237281452374,
          -0.8920804965813985,
          -1.0150688994534571,
          -1.069584495328057,
          -1.0733729063401134,
          -1.039479383105552,
          -0.9771262230837806,
          -0.8929381245685519,
          -0.7918267669651687,
          -0.6775707400599782,
          -0.5531880892804801,
          -0.4211840160965372,
          -0.2837186776965292,
          -0.14272505928832493
        ],
        "32": [
          -6.649213432875272e-09,
          0.1317893635536806,
          0.2623473123829469,
          0.390402204488262,
          0.5145945559696078,
          0.6334194783979525,
          0.745144797108606,
          0.8476911610702749,
          0.9384467453493409,
          1.013960049918357,
          1.0694124378922485,
          1.0976320061222036,
          1.0870827662352762,
          1.0169430803763913,
          0.8453431815279518,
          0.5070215419102556,
          1.9085518944506067e-07,
          -0.5070219034810142,
          -0.8453426621132784,
          -1.016943779982955,
          -1.087082149871088,
          -1.0976322395174891,
          -1.0694123555439137,
          -1.0139601377167178,
          -0.9384465618017404,
          -0.8476913105846761,
          -0.745144728625559,
          -0.6334195464812098,
          -0.5145945582911785,
          -0.39040211385364465,
          -0.2623474333938118,
          -0.1317892509248246
        ],
        "40": [
          -5.701057183774821e-09,
          0.1225413081260304,
          0.24415382859468923,
          0.36388500351837694,
          0.4807295872616514,
          0.5935948183728179,
          0.7012500389560566,
          0.8022517293480453,
          0.8948282433830446,
          0.9766857567828493,
          1.0446765293595281,
          1.094159044537895,
          1.1176366272949423,
          1.1030229485951992,
          1.0229997744670087,
          0.7313914367430416,
          3.0028769914633666e-07,
          -0.7313919364246266,
          -1.022999268889889,
          -1.1030236123532193,
          -1.1176358499613972,
          -1.0941595217402926,
          -1.0446763410552153,
          -0.9766858211671077,
          -0.8948281039777201,
          -0.8022518947297533,
          -0.7012499529597548,
          -0.5935948953598077,
          -0.4807295605145626,
          -0.36388494020490814,
          -0.24415393392874532,
          -0.12254120233470754
        ],
        "48": [
          -4.901627149041767e-09,
          0.11446072376060562,
          0.22818907703344732,
          0.34043923491442696,
          0.45043489317520563,
          0.5573489912420294,
          0.6602740231972335,
          0.7581770699246165,
          0.849832672677738,
          0.9337095667733911,
          1.0077727584496057,
          1.0692237258971786,
          1.1139072984919558,
          1.1286116014728185,
          1.129302513694622,
          1.1161289555556928,
          5.858635451500244e-07,
          -1.1161298286835872,
          -1.1293019562106772,
          -1.1286121460770409,
          -1.1139065212050698,
          -1.0692244046381327,
          -1.0077723835349528,
          -0.9337096803803447,
          -0.849832572840681,
          -0.7581772299971321,
          -0.6602739226961856,
          -0.5573490736076188,
          -0.4504348452775009,
          -0.3404391959861604,
          -0.2281891674117208,
          -0.11446062434939361
        ],
        "51": [
          -4.63384929976199e-09,
          0.11165212724196176,
          0.2226289214813243,
          0.33224430240658376,
          0.4397875665565991,
          0.5445069403005874,
          0.645585394068427,
          0.7421036019613344,
          0.8329853937330696,
          0.9169074984520429,
          0.9921294305200976,
          1.0562252654358275,
          1.107051911417914,
          1.1285746527498155,
          1.1226522619850585,
          1.3159616240027303,
          8.162903846198462e-07,
          -1.3159627864707188,
          -1.1226516390571941,
          -1.1285751615988404,
          -1.1070511713620226,
          -1.056225988765944,
          -0.9921289797588261,
          -0.9169076505575733,
          -0.8329853010440318,
          -0.7421037565095551,
          -0.6455852896282551,
          -0.5445070240715403,
          -0.4397875124404067,
          -0.33224427179998955,
          -0.22262900645991593,
          -0.11165203011867346
        ]
      },
      "_source": "solver"
    }
  ],
  "analysis": [
    {
      "final_error_epsilon": 2.7385211849251394e-05,
      "max_error_epsilon": 2.7385211849251394e-05,
      "classical_wall_time_s": 0.0021963119506835938,
      "method_wall_time_s": 0.31682348251342773,
      "speedup_ratio": 0.006932289024979418,
      "n_pauli_terms": 252,
      "shots": 0,
      "t1": null,
      "t2": null,
      "backend_name": null,
      "backend_type": "sim",
      "coupling_map": "default",
      "optimization_level": 1,
      "seed": null,
      "total_pauli_decomp_time": 0,
      "total_circuit_construction_time": 0,
      "total_transpilation_time": 0,
      "total_execution_time": 0,
      "total_sign_recovery_time": 0,
      "total_metric_transpile_time": 0,
      "n_circuits_executed": 0,
      "avg_circuit_depth": null,
      "avg_gate_count": null,
      "avg_cx_gates": null,
      "avg_sign_recovery_depth_per_circuit": null,
      "avg_sign_recovery_cx_per_circuit": null,
      "total_sign_recovery_cx": 0,
      "n_qubits": null,
      "circuit_metrics_n_available": 0,
      "circuit_metrics_n_total": 51,
      "sign_recovery": "none",
      "per_step_metrics": [
        {
          "method": "tebd",
          "mpo_bond_dims": [
            4,
            10,
            10,
            4
          ],
          "mps_bond_dims_in": [
            1,
            2,
            2,
            2
          ],
          "mps_bond_dims_out": [
            2,
            3,
            4,
            2
          ],
          "max_bond": null,
          "cutoff": 1e-14
        },
        {
          "method": "tebd",
          "mpo_bond_dims": [
            4,
            11,
            13,
            4
          ],
          "mps_bond_dims_in": [
            2,
            3,
            4,
            2
          ],
          "mps_bond_dims_out": [
            2,
            4,
            4,
            2
          ],
          "max_bond": null,
          "cutoff": 1e-14
        },
        {
          "method": "tebd",
          "mpo_bond_dims": [
            4,
            13,
            13,
            4
          ],
          "mps_bond_dims_in": [
            2,
            4,
            4,
            2
          ],
          "mps_bond_dims_out": [
            2,
            4,
            4,
            2
          ],
          "max_bond": null,
          "cutoff": 1e-14
        },
        {
          "method": "tebd",
          "mpo_bond_dims": [
            4,
            14,
            13,
            4
          ],
          "mps_bond_dims_in": [
            2,
            4,
            4,
            2
          ],
          "mps_bond_dims_out": [
            2,
            4,
            4,
            2
          ],
          "max_bond": null,
          "cutoff": 1e-14
        },
        {
          "method": "tebd",
          "mpo_bond_dims": [
            4,
            16,
            13,
            4
          ],
          "mps_bond_dims_in": [
            2,
            4,
            4,
            2
          ],
          "mps_bond_dims_out": [
            2,
            4,
            4,
            2
          ],
          "max_bond": null,
          "cutoff": 1e-14
        },
        {
          "method": "tebd",
          "mpo_bond_dims": [
            4,
            16,
            13,
            4
          ],
          "mps_bond_dims_in": [
            2,
            4,
            4,
            2
          ],
          "mps_bond_dims_out": [
            2,
            4,
            4,
            2
          ],
          "max_bond": null,
          "cutoff": 1e-14
        },
        {
          "method": "tebd",
          "mpo_bond_dims": [
            4,
            16,
            13,
            4
          ],
          "mps_bond_dims_in": [
            2,
            4,
            4,
            2
          ],
          "mps_bond_dims_out": [
            2,
            4,
            4,
            2
          ],
          "max_bond": null,
          "cutoff": 1e-14
        },
        {
          "method": "tebd",
          "mpo_bond_dims": [
            4,
            16,
            14,
            4
          ],
          "mps_bond_dims_in": [
            2,
            4,
            4,
            2
          ],
          "mps_bond_dims_out": [
            2,
            4,
            4,
            2
          ],
          "max_bond": null,
          "cutoff": 1e-14
        },
        {
          "method": "tebd",
          "mpo_bond_dims": [
            4,
            16,
            14,
            4
          ],
          "mps_bond_dims_in": [
            2,
            4,
            4,
            2
          ],
          "mps_bond_dims_out": [
            2,
            4,
            4,
            2
          ],
          "max_bond": null,
          "cutoff": 1e-14
        },
        {
          "method": "tebd",
          "mpo_bond_dims": [
            4,
            16,
            14,
            4
          ],
          "mps_bond_dims_in": [
            2,
            4,
            4,
            2
          ],
          "mps_bond_dims_out": [
            2,
            4,
            4,
            2
          ],
          "max_bond": null,
          "cutoff": 1e-14
        },
        {
          "method": "tebd",
          "mpo_bond_dims": [
            4,
            16,
            14,
            4
          ],
          "mps_bond_dims_in": [
            2,
            4,
            4,
            2
          ],
          "mps_bond_dims_out": [
            2,
            4,
            4,
            2
          ],
          "max_bond": null,
          "cutoff": 1e-14
        },
        {
          "method": "tebd",
          "mpo_bond_dims": [
            4,
            16,
            14,
            4
          ],
          "mps_bond_dims_in": [
            2,
            4,
            4,
            2
          ],
          "mps_bond_dims_out": [
            2,
            4,
            4,
            2
          ],
          "max_bond": null,
          "cutoff": 1e-14
        },
        {
          "method": "tebd",
          "mpo_bond_dims": [
            4,
            16,
            14,
            4
          ],
          "mps_bond_dims_in": [
            2,
            4,
            4,
            2
          ],
          "mps_bond_dims_out": [
            2,
            4,
            4,
            2
          ],
          "max_bond": null,
          "cutoff": 1e-14
        },
        {
          "method": "tebd",
          "mpo_bond_dims": [
            4,
            16,
            14,
            4
          ],
          "mps_bond_dims_in": [
            2,
            4,
            4,
            2
          ],
          "mps_bond_dims_out": [
            2,
            4,
            4,
            2
          ],
          "max_bond": null,
          "cutoff": 1e-14
        },
        {
          "method": "tebd",
          "mpo_bond_dims": [
            4,
            16,
            15,
            4
          ],
          "mps_bond_dims_in": [
            2,
            4,
            4,
            2
          ],
          "mps_bond_dims_out": [
            2,
            4,
            4,
            2
          ],
          "max_bond": null,
          "cutoff": 1e-14
        },
        {
          "method": "tebd",
          "mpo_bond_dims": [
            4,
            16,
            15,
            4
          ],
          "mps_bond_dims_in": [
            2,
            4,
            4,
            2
          ],
          "mps_bond_dims_out": [
            2,
            4,
            4,
            2
          ],
          "max_bond": null,
          "cutoff": 1e-14
        },
        {
          "method": "tebd",
          "mpo_bond_dims": [
            4,
            16,
            16,
            4
          ],
          "mps_bond_dims_in": [
            2,
            4,
            4,
            2
          ],
          "mps_bond_dims_out": [
            2,
            4,
            4,
            2
          ],
          "max_bond": null,
          "cutoff": 1e-14
        },
        {
          "method": "tebd",
          "mpo_bond_dims": [
            4,
            16,
            16,
            4
          ],
          "mps_bond_dims_in": [
            2,
            4,
            4,
            2
          ],
          "mps_bond_dims_out": [
            2,
            4,
            4,
            2
          ],
          "max_bond": null,
          "cutoff": 1e-14
        },
        {
          "method": "tebd",
          "mpo_bond_dims": [
            4,
            16,
            16,
            4
          ],
          "mps_bond_dims_in": [
            2,
            4,
            4,
            2
          ],
          "mps_bond_dims_out": [
            2,
            4,
            4,
            2
          ],
          "max_bond": null,
          "cutoff": 1e-14
        },
        {
          "method": "tebd",
          "mpo_bond_dims": [
            4,
            16,
            16,
            4
          ],
          "mps_bond_dims_in": [
            2,
            4,
            4,
            2
          ],
          "mps_bond_dims_out": [
            2,
            4,
            4,
            2
          ],
          "max_bond": null,
          "cutoff": 1e-14
        },
        {
          "method": "tebd",
          "mpo_bond_dims": [
            4,
            16,
            16,
            4
          ],
          "mps_bond_dims_in": [
            2,
            4,
            4,
            2
          ],
          "mps_bond_dims_out": [
            2,
            4,
            4,
            2
          ],
          "max_bond": null,
          "cutoff": 1e-14
        },
        {
          "method": "tebd",
          "mpo_bond_dims": [
            4,
            16,
            16,
            4
          ],
          "mps_bond_dims_in": [
            2,
            4,
            4,
            2
          ],
          "mps_bond_dims_out": [
            2,
            4,
            4,
            2
          ],
          "max_bond": null,
          "cutoff": 1e-14
        },
        {
          "method": "tebd",
          "mpo_bond_dims": [
            4,
            16,
            16,
            4
          ],
          "mps_bond_dims_in": [
            2,
            4,
            4,
            2
          ],
          "mps_bond_dims_out": [
            2,
            4,
            4,
            2
          ],
          "max_bond": null,
          "cutoff": 1e-14
        },
        {
          "method": "tebd",
          "mpo_bond_dims": [
            4,
            16,
            16,
            4
          ],
          "mps_bond_dims_in": [
            2,
            4,
            4,
            2
          ],
          "mps_bond_dims_out": [
            2,
            4,
            4,
            2
          ],
          "max_bond": null,
          "cutoff": 1e-14
        },
        {
          "method": "tebd",
          "mpo_bond_dims": [
            4,
            16,
            16,
            4
          ],
          "mps_bond_dims_in": [
            2,
            4,
            4,
            2
          ],
          "mps_bond_dims_out": [
            2,
            4,
            4,
            2
          ],
          "max_bond": null,
          "cutoff": 1e-14
        },
        {
          "method": "tebd",
          "mpo_bond_dims": [
            4,
            16,
            16,
            4
          ],
          "mps_bond_dims_in": [
            2,
            4,
            4,
            2
          ],
          "mps_bond_dims_out": [
            2,
            4,
            4,
            2
          ],
          "max_bond": null,
          "cutoff": 1e-14
        },
        {
          "method": "tebd",
          "mpo_bond_dims": [
            4,
            16,
            16,
            4
          ],
          "mps_bond_dims_in": [
            2,
            4,
            4,
            2
          ],
          "mps_bond_dims_out": [
            2,
            4,
            4,
            2
          ],
          "max_bond": null,
          "cutoff": 1e-14
        },
        {
          "method": "tebd",
          "mpo_bond_dims": [
            4,
            16,
            16,
            4
          ],
          "mps_bond_dims_in": [
            2,
            4,
            4,
            2
          ],
          "mps_bond_dims_out": [
            2,
            4,
            4,
            2
          ],
          "max_bond": null,
          "cutoff": 1e-14
        },
        {
          "method": "tebd",
          "mpo_bond_dims": [
            4,
            16,
            16,
            4
          ],
          "mps_bond_dims_in": [
            2,
            4,
            4,
            2
          ],
          "mps_bond_dims_out": [
            2,
            4,
            4,
            2
          ],
          "max_bond": null,
          "cutoff": 1e-14
        },
        {
          "method": "tebd",
          "mpo_bond_dims": [
            4,
            16,
            16,
            4
          ],
          "mps_bond_dims_in": [
            2,
            4,
            4,
            2
          ],
          "mps_bond_dims_out": [
            2,
            4,
            4,
            2
          ],
          "max_bond": null,
          "cutoff": 1e-14
        },
        {
          "method": "tebd",
          "mpo_bond_dims": [
            4,
            16,
            16,
            4
          ],
          "mps_bond_dims_in": [
            2,
            4,
            4,
            2
          ],
          "mps_bond_dims_out": [
            2,
            4,
            4,
            2
          ],
          "max_bond": null,
          "cutoff": 1e-14
        },
        {
          "method": "tebd",
          "mpo_bond_dims": [
            4,
            16,
            16,
            4
          ],
          "mps_bond_dims_in": [
            2,
            4,
            4,
            2
          ],
          "mps_bond_dims_out": [
            2,
            4,
            4,
            2
          ],
          "max_bond": null,
          "cutoff": 1e-14
        },
        {
          "method": "tebd",
          "mpo_bond_dims": [
            4,
            16,
            16,
            4
          ],
          "mps_bond_dims_in": [
            2,
            4,
            4,
            2
          ],
          "mps_bond_dims_out": [
            2,
            4,
            4,
            2
          ],
          "max_bond": null,
          "cutoff": 1e-14
        },
        {
          "method": "tebd",
          "mpo_bond_dims": [
            4,
            16,
            16,
            4
          ],
          "mps_bond_dims_in": [
            2,
            4,
            4,
            2
          ],
          "mps_bond_dims_out": [
            2,
            4,
            4,
            2
          ],
          "max_bond": null,
          "cutoff": 1e-14
        },
        {
          "method": "tebd",
          "mpo_bond_dims": [
            4,
            16,
            16,
            4
          ],
          "mps_bond_dims_in": [
            2,
            4,
            4,
            2
          ],
          "mps_bond_dims_out": [
            2,
            4,
            4,
            2
          ],
          "max_bond": null,
          "cutoff": 1e-14
        },
        {
          "method": "tebd",
          "mpo_bond_dims": [
            4,
            16,
            16,
            4
          ],
          "mps_bond_dims_in": [
            2,
            4,
            4,
            2
          ],
          "mps_bond_dims_out": [
            2,
            4,
            4,
            2
          ],
          "max_bond": null,
          "cutoff": 1e-14
        },
        {
          "method": "tebd",
          "mpo_bond_dims": [
            4,
            16,
            16,
            4
          ],
          "mps_bond_dims_in": [
            2,
            4,
            4,
            2
          ],
          "mps_bond_dims_out": [
            2,
            4,
            4,
            2
          ],
          "max_bond": null,
          "cutoff": 1e-14
        },
        {
          "method": "tebd",
          "mpo_bond_dims": [
            4,
            16,
            16,
            4
          ],
          "mps_bond_dims_in": [
            2,
            4,
            4,
            2
          ],
          "mps_bond_dims_out": [
            2,
            4,
            4,
            2
          ],
          "max_bond": null,
          "cutoff": 1e-14
        },
        {
          "method": "tebd",
          "mpo_bond_dims": [
            4,
            16,
            16,
            4
          ],
          "mps_bond_dims_in": [
            2,
            4,
            4,
            2
          ],
          "mps_bond_dims_out": [
            2,
            4,
            4,
            2
          ],
          "max_bond": null,
          "cutoff": 1e-14
        },
        {
          "method": "tebd",
          "mpo_bond_dims": [
            4,
            16,
            16,
            4
          ],
          "mps_bond_dims_in": [
            2,
            4,
            4,
            2
          ],
          "mps_bond_dims_out": [
            2,
            4,
            4,
            2
          ],
          "max_bond": null,
          "cutoff": 1e-14
        },
        {
          "method": "tebd",
          "mpo_bond_dims": [
            4,
            16,
            16,
            4
          ],
          "mps_bond_dims_in": [
            2,
            4,
            4,
            2
          ],
          "mps_bond_dims_out": [
            2,
            4,
            4,
            2
          ],
          "max_bond": null,
          "cutoff": 1e-14
        },
        {
          "method": "tebd",
          "mpo_bond_dims": [
            4,
            16,
            16,
            4
          ],
          "mps_bond_dims_in": [
            2,
            4,
            4,
            2
          ],
          "mps_bond_dims_out": [
            2,
            4,
            4,
            2
          ],
          "max_bond": null,
          "cutoff": 1e-14
        },
        {
          "method": "tebd",
          "mpo_bond_dims": [
            4,
            16,
            16,
            4
          ],
          "mps_bond_dims_in": [
            2,
            4,
            4,
            2
          ],
          "mps_bond_dims_out": [
            2,
            4,
            4,
            2
          ],
          "max_bond": null,
          "cutoff": 1e-14
        },
        {
          "method": "tebd",
          "mpo_bond_dims": [
            4,
            16,
            16,
            4
          ],
          "mps_bond_dims_in": [
            2,
            4,
            4,
            2
          ],
          "mps_bond_dims_out": [
            2,
            4,
            4,
            2
          ],
          "max_bond": null,
          "cutoff": 1e-14
        },
        {
          "method": "tebd",
          "mpo_bond_dims": [
            4,
            16,
            16,
            4
          ],
          "mps_bond_dims_in": [
            2,
            4,
            4,
            2
          ],
          "mps_bond_dims_out": [
            2,
            4,
            4,
            2
          ],
          "max_bond": null,
          "cutoff": 1e-14
        },
        {
          "method": "tebd",
          "mpo_bond_dims": [
            4,
            16,
            16,
            4
          ],
          "mps_bond_dims_in": [
            2,
            4,
            4,
            2
          ],
          "mps_bond_dims_out": [
            2,
            4,
            4,
            2
          ],
          "max_bond": null,
          "cutoff": 1e-14
        },
        {
          "method": "tebd",
          "mpo_bond_dims": [
            4,
            16,
            16,
            4
          ],
          "mps_bond_dims_in": [
            2,
            4,
            4,
            2
          ],
          "mps_bond_dims_out": [
            2,
            4,
            4,
            2
          ],
          "max_bond": null,
          "cutoff": 1e-14
        },
        {
          "method": "tebd",
          "mpo_bond_dims": [
            4,
            16,
            16,
            4
          ],
          "mps_bond_dims_in": [
            2,
            4,
            4,
            2
          ],
          "mps_bond_dims_out": [
            2,
            4,
            4,
            2
          ],
          "max_bond": null,
          "cutoff": 1e-14
        },
        {
          "method": "tebd",
          "mpo_bond_dims": [
            4,
            16,
            16,
            4
          ],
          "mps_bond_dims_in": [
            2,
            4,
            4,
            2
          ],
          "mps_bond_dims_out": [
            2,
            4,
            4,
            2
          ],
          "max_bond": null,
          "cutoff": 1e-14
        },
        {
          "method": "tebd",
          "mpo_bond_dims": [
            4,
            16,
            16,
            4
          ],
          "mps_bond_dims_in": [
            2,
            4,
            4,
            2
          ],
          "mps_bond_dims_out": [
            2,
            4,
            4,
            2
          ],
          "max_bond": null,
          "cutoff": 1e-14
        },
        {
          "method": "tebd",
          "mpo_bond_dims": [
            4,
            16,
            16,
            4
          ],
          "mps_bond_dims_in": [
            2,
            4,
            4,
            2
          ],
          "mps_bond_dims_out": [
            2,
            4,
            4,
            2
          ],
          "max_bond": null,
          "cutoff": 1e-14
        }
      ],
      "_source": "solver"
    }
  ],
  "code": [
    {
      "_source": "sweep",
      "entry_point": "-c",
      "interpreter": "bash",
      "library_versions_before": {
        "type": "venv",
        "path": "/autofs/nccs-svm1_home1/ishangore/q8020/q8020-mps-burgers/.venv",
        "packages": {
          "setuptools": "82.0.1",
          "packaging": "26.2",
          "pip": "26.1.2",
          "wheel": "0.47.0",
          "websockets": "16.0",
          "watchdog": "6.0.0",
          "urllib3": "2.7.0",
          "typing_extensions": "4.15.0",
          "toml": "0.10.2",
          "tenacity": "9.1.4",
          "subprocess-tee": "0.4.2",
          "smmap": "5.0.3",
          "six": "1.17.0",
          "rpds-py": "2026.5.1",
          "python-multipart": "0.0.30",
          "pyparsing": "3.3.2",
          "pyarrow": "24.0.0",
          "protobuf": "7.35.0",
          "pillow": "12.2.0",
          "numpy": "2.4.6",
          "narwhals": "2.22.0",
          "MarkupSafe": "3.0.3",
          "kiwisolver": "1.5.0",
          "itsdangerous": "2.2.0",
          "idna": "3.18",
          "httptools": "0.8.0",
          "h11": "0.16.0",
          "fonttools": "4.63.0",
          "duckdb": "1.5.3",
          "cycler": "0.12.1",
          "click": "8.4.1",
          "charset-normalizer": "3.4.7",
          "certifi": "2026.5.20",
          "cachetools": "7.1.4",
          "blinker": "1.9.0",
          "attrs": "26.1.0",
          "uvicorn": "0.48.0",
          "requests": "2.34.2",
          "referencing": "0.37.0",
          "python-dateutil": "2.9.0.post0",
          "plotly": "6.7.0",
          "Jinja2": "3.1.6",
          "gitdb": "4.0.12",
          "contourpy": "1.3.3",
          "anyio": "4.13.0",
          "starlette": "1.2.1",
          "pydeck": "0.9.2",
          "pandas": "3.0.3",
          "matplotlib": "3.10.9",
          "jsonschema-specifications": "2025.9.1",
          "GitPython": "3.1.50",
          "jsonschema": "4.26.0",
          "altair": "6.1.0",
          "streamlit": "1.58.0",
          "q8020-cfd-metautil": "0.1.0",
          "typing-inspection": "0.4.2",
          "stevedore": "5.8.0",
          "scipy": "1.17.1",
          "rustworkx": "0.17.1",
          "PyJWT": "2.13.0",
          "pydantic_core": "2.46.4",
          "pycparser": "3.0",
          "pybase64": "1.4.3",
          "psutil": "7.2.2",
          "orjson": "3.11.9",
          "dill": "0.4.1",
          "annotated-types": "0.7.0",
          "qiskit": "2.4.1",
          "pydantic": "2.13.4",
          "ibm-cloud-sdk-core": "3.24.4",
          "cffi": "2.0.0",
          "samplomatic": "0.19.0",
          "qiskit-aer": "0.17.2",
          "ibm-platform-services": "0.75.0",
          "cryptography": "48.0.0",
          "pyspnego": "0.12.1",
          "ibm-quantum-schemas": "0.7.20260419",
          "requests_ntlm": "1.3.0",
          "qiskit-ibm-runtime": "0.47.0",
          "q8020-cfd-qutil": "0.1.0",
          "tqdm": "4.67.3",
          "toolz": "1.1.0",
          "Pygments": "2.20.0",
          "pluggy": "1.6.0",
          "llvmlite": "0.47.0",
          "iniconfig": "2.3.0",
          "autoray": "0.8.10",
          "pytest": "9.0.3",
          "numba": "0.65.1",
          "cytoolz": "1.1.0",
          "cotengra": "0.8.0",
          "quimb": "1.14.0",
          "q8020-mps-burgers": "0.1.0"
        },
        "package_count": 93,
        "timestamp": "2026-06-03T18:33:04.413030Z"
      },
      "library_versions_after": {
        "type": "venv",
        "path": "/autofs/nccs-svm1_home1/ishangore/q8020/q8020-mps-burgers/.venv",
        "packages": {
          "setuptools": "82.0.1",
          "packaging": "26.2",
          "pip": "26.1.2",
          "wheel": "0.47.0",
          "websockets": "16.0",
          "watchdog": "6.0.0",
          "urllib3": "2.7.0",
          "typing_extensions": "4.15.0",
          "toml": "0.10.2",
          "tenacity": "9.1.4",
          "subprocess-tee": "0.4.2",
          "smmap": "5.0.3",
          "six": "1.17.0",
          "rpds-py": "2026.5.1",
          "python-multipart": "0.0.30",
          "pyparsing": "3.3.2",
          "pyarrow": "24.0.0",
          "protobuf": "7.35.0",
          "pillow": "12.2.0",
          "numpy": "2.4.6",
          "narwhals": "2.22.0",
          "MarkupSafe": "3.0.3",
          "kiwisolver": "1.5.0",
          "itsdangerous": "2.2.0",
          "idna": "3.18",
          "httptools": "0.8.0",
          "h11": "0.16.0",
          "fonttools": "4.63.0",
          "duckdb": "1.5.3",
          "cycler": "0.12.1",
          "click": "8.4.1",
          "charset-normalizer": "3.4.7",
          "certifi": "2026.5.20",
          "cachetools": "7.1.4",
          "blinker": "1.9.0",
          "attrs": "26.1.0",
          "uvicorn": "0.48.0",
          "requests": "2.34.2",
          "referencing": "0.37.0",
          "python-dateutil": "2.9.0.post0",
          "plotly": "6.7.0",
          "Jinja2": "3.1.6",
          "gitdb": "4.0.12",
          "contourpy": "1.3.3",
          "anyio": "4.13.0",
          "starlette": "1.2.1",
          "pydeck": "0.9.2",
          "pandas": "3.0.3",
          "matplotlib": "3.10.9",
          "jsonschema-specifications": "2025.9.1",
          "GitPython": "3.1.50",
          "jsonschema": "4.26.0",
          "altair": "6.1.0",
          "streamlit": "1.58.0",
          "q8020-cfd-metautil": "0.1.0",
          "typing-inspection": "0.4.2",
          "stevedore": "5.8.0",
          "scipy": "1.17.1",
          "rustworkx": "0.17.1",
          "PyJWT": "2.13.0",
          "pydantic_core": "2.46.4",
          "pycparser": "3.0",
          "pybase64": "1.4.3",
          "psutil": "7.2.2",
          "orjson": "3.11.9",
          "dill": "0.4.1",
          "annotated-types": "0.7.0",
          "qiskit": "2.4.1",
          "pydantic": "2.13.4",
          "ibm-cloud-sdk-core": "3.24.4",
          "cffi": "2.0.0",
          "samplomatic": "0.19.0",
          "qiskit-aer": "0.17.2",
          "ibm-platform-services": "0.75.0",
          "cryptography": "48.0.0",
          "pyspnego": "0.12.1",
          "ibm-quantum-schemas": "0.7.20260419",
          "requests_ntlm": "1.3.0",
          "qiskit-ibm-runtime": "0.47.0",
          "q8020-cfd-qutil": "0.1.0",
          "tqdm": "4.67.3",
          "toolz": "1.1.0",
          "Pygments": "2.20.0",
          "pluggy": "1.6.0",
          "llvmlite": "0.47.0",
          "iniconfig": "2.3.0",
          "autoray": "0.8.10",
          "pytest": "9.0.3",
          "numba": "0.65.1",
          "cytoolz": "1.1.0",
          "cotengra": "0.8.0",
          "quimb": "1.14.0",
          "q8020-mps-burgers": "0.1.0"
        },
        "package_count": 93,
        "timestamp": "2026-06-03T18:33:09.076716Z"
      }
    }
  ],
  "experiment": [
    {
      "_source": "sweep",
      "name": "tebd_q5",
      "experiment_id": "64fce4fa",
      "workflow_id": "_b56add80",
      "timestamp": "2026-06-03T18:33:04.415416Z",
      "user": {
        "username": "ishangore",
        "hostname": "frontier10357"
      }
    }
  ],
  "backend": []
}