{
  "final_error_epsilon": 0.19927358622892202,
  "max_error_epsilon": 0.19927358622892202,
  "classical_wall_time_s": 0.0001480579376220703,
  "method_wall_time_s": 4.7761290073394775,
  "speedup_ratio": 3.099956835222618e-05,
  "n_pauli_terms": null,
  "shots": 150000,
  "t1": null,
  "t2": null,
  "backend_name": null,
  "backend_type": "sim",
  "coupling_map": "default",
  "optimization_level": 1,
  "seed": 1234,
  "total_pauli_decomp_time": 0,
  "total_circuit_construction_time": 0.010195016860961914,
  "total_transpilation_time": 0.3226592540740967,
  "total_execution_time": 0.09268808364868164,
  "total_sign_recovery_time": 0,
  "total_metric_transpile_time": 1.8016290664672852,
  "n_circuits_executed": 6,
  "avg_circuit_depth": 227.0,
  "avg_gate_count": 288.0,
  "avg_cx_gates": 71.0,
  "avg_sign_recovery_depth_per_circuit": null,
  "avg_sign_recovery_cx_per_circuit": null,
  "total_sign_recovery_cx": 0,
  "n_qubits": 5,
  "circuit_metrics_n_available": 6,
  "circuit_metrics_n_total": 6,
  "sign_recovery": "none",
  "per_step_metrics": [
    {
      "shots": 150000,
      "n_kept": 148881,
      "p_success": 0.99254,
      "n_steps": 1,
      "step": 1,
      "segment_idx": 0,
      "segment_size": 1,
      "cumulative_norm": 2.2084884172423176,
      "transpile": {
        "wall_time": 0.14854979515075684,
        "optimization_level": 1,
        "before": {
          "depth": 13,
          "num_qubits": 5,
          "gate_counts": {
            "measure": 4,
            "unitary": 3,
            "cry": 3,
            "ccry": 3,
            "qft": 1,
            "c3ry": 1,
            "qft_dg": 1
          }
        },
        "after": {
          "depth": 45,
          "num_qubits": 5,
          "gate_counts": {
            "cu": 16,
            "cx": 12,
            "h": 6,
            "cp": 6,
            "measure": 4,
            "unitary": 3,
            "cry": 3,
            "swap": 2
          }
        }
      },
      "execute": {
        "wall_time": 0.019430875778198242,
        "shots_requested": 150000,
        "shots_executed": 150000,
        "backend_time": 0.01585
      },
      "circuit_construction_time_s": 0.0026857852935791016,
      "transpilation_time_s": 0.14854979515075684,
      "metric_transpile_time_s": 1.8016290664672852,
      "execution_time_s": 0.019430875778198242,
      "n_circuits": 1,
      "circuit_depth": 227,
      "gate_counts": {
        "rz": 118,
        "sx": 94,
        "cx": 71,
        "measure": 4,
        "x": 1
      },
      "n_qubits": 5,
      "circuit_metrics_available": true,
      "circuit_metrics_from_segment": 0,
      "circuit_metrics_exact": true
    },
    {
      "shots": 150000,
      "n_kept": 149093,
      "p_success": 0.9939533333333334,
      "n_steps": 2,
      "step": 2,
      "segment_idx": 1,
      "segment_size": 1,
      "cumulative_norm": 2.2018012965694154,
      "transpile": {
        "wall_time": 0.036679983139038086,
        "optimization_level": 1,
        "before": {
          "depth": 13,
          "num_qubits": 5,
          "gate_counts": {
            "measure": 4,
            "unitary": 3,
            "cry": 3,
            "ccry": 3,
            "qft": 1,
            "c3ry": 1,
            "qft_dg": 1
          }
        },
        "after": {
          "depth": 45,
          "num_qubits": 5,
          "gate_counts": {
            "cu": 16,
            "cx": 12,
            "h": 6,
            "cp": 6,
            "measure": 4,
            "unitary": 3,
            "cry": 3,
            "swap": 2
          }
        }
      },
      "execute": {
        "wall_time": 0.014519929885864258,
        "shots_requested": 150000,
        "shots_executed": 150000,
        "backend_time": 0.01332725
      },
      "circuit_construction_time_s": 0.001947164535522461,
      "transpilation_time_s": 0.036679983139038086,
      "metric_transpile_time_s": 0.0,
      "execution_time_s": 0.014519929885864258,
      "n_circuits": 1,
      "circuit_depth": 227,
      "gate_counts": {
        "rz": 118,
        "sx": 94,
        "cx": 71,
        "measure": 4,
        "x": 1
      },
      "n_qubits": 5,
      "circuit_metrics_available": true,
      "circuit_metrics_from_segment": 0,
      "circuit_metrics_exact": false
    },
    {
      "shots": 150000,
      "n_kept": 149286,
      "p_success": 0.99524,
      "n_steps": 3,
      "step": 3,
      "segment_idx": 2,
      "segment_size": 1,
      "cumulative_norm": 2.196554758656106,
      "transpile": {
        "wall_time": 0.034989118576049805,
        "optimization_level": 1,
        "before": {
          "depth": 13,
          "num_qubits": 5,
          "gate_counts": {
            "measure": 4,
            "unitary": 3,
            "cry": 3,
            "ccry": 3,
            "qft": 1,
            "c3ry": 1,
            "qft_dg": 1
          }
        },
        "after": {
          "depth": 45,
          "num_qubits": 5,
          "gate_counts": {
            "cu": 16,
            "cx": 12,
            "h": 6,
            "cp": 6,
            "measure": 4,
            "unitary": 3,
            "cry": 3,
            "swap": 2
          }
        }
      },
      "execute": {
        "wall_time": 0.01493215560913086,
        "shots_requested": 150000,
        "shots_executed": 150000,
        "backend_time": 0.013721
      },
      "circuit_construction_time_s": 0.0013570785522460938,
      "transpilation_time_s": 0.034989118576049805,
      "metric_transpile_time_s": 0.0,
      "execution_time_s": 0.01493215560913086,
      "n_circuits": 1,
      "circuit_depth": 227,
      "gate_counts": {
        "rz": 118,
        "sx": 94,
        "cx": 71,
        "measure": 4,
        "x": 1
      },
      "n_qubits": 5,
      "circuit_metrics_available": true,
      "circuit_metrics_from_segment": 0,
      "circuit_metrics_exact": false
    },
    {
      "shots": 150000,
      "n_kept": 149435,
      "p_success": 0.9962333333333333,
      "n_steps": 4,
      "step": 4,
      "segment_idx": 3,
      "segment_size": 1,
      "cumulative_norm": 2.1924140109778913,
      "transpile": {
        "wall_time": 0.03465914726257324,
        "optimization_level": 1,
        "before": {
          "depth": 13,
          "num_qubits": 5,
          "gate_counts": {
            "measure": 4,
            "unitary": 3,
            "cry": 3,
            "ccry": 3,
            "qft": 1,
            "c3ry": 1,
            "qft_dg": 1
          }
        },
        "after": {
          "depth": 45,
          "num_qubits": 5,
          "gate_counts": {
            "cu": 16,
            "cx": 12,
            "h": 6,
            "cp": 6,
            "measure": 4,
            "unitary": 3,
            "cry": 3,
            "swap": 2
          }
        }
      },
      "execute": {
        "wall_time": 0.014503955841064453,
        "shots_requested": 150000,
        "shots_executed": 150000,
        "backend_time": 0.013326792
      },
      "circuit_construction_time_s": 0.0014879703521728516,
      "transpilation_time_s": 0.03465914726257324,
      "metric_transpile_time_s": 0.0,
      "execution_time_s": 0.014503955841064453,
      "n_circuits": 1,
      "circuit_depth": 227,
      "gate_counts": {
        "rz": 118,
        "sx": 94,
        "cx": 71,
        "measure": 4,
        "x": 1
      },
      "n_qubits": 5,
      "circuit_metrics_available": true,
      "circuit_metrics_from_segment": 0,
      "circuit_metrics_exact": false
    },
    {
      "shots": 150000,
      "n_kept": 149558,
      "p_success": 0.9970533333333333,
      "n_steps": 5,
      "step": 5,
      "segment_idx": 4,
      "segment_size": 1,
      "cumulative_norm": 2.189181471273985,
      "transpile": {
        "wall_time": 0.03387594223022461,
        "optimization_level": 1,
        "before": {
          "depth": 13,
          "num_qubits": 5,
          "gate_counts": {
            "measure": 4,
            "unitary": 3,
            "cry": 3,
            "ccry": 3,
            "qft": 1,
            "c3ry": 1,
            "qft_dg": 1
          }
        },
        "after": {
          "depth": 45,
          "num_qubits": 5,
          "gate_counts": {
            "cu": 16,
            "cx": 12,
            "h": 6,
            "cp": 6,
            "measure": 4,
            "unitary": 3,
            "cry": 3,
            "swap": 2
          }
        }
      },
      "execute": {
        "wall_time": 0.013935089111328125,
        "shots_requested": 150000,
        "shots_executed": 150000,
        "backend_time": 0.012775833
      },
      "circuit_construction_time_s": 0.001377105712890625,
      "transpilation_time_s": 0.03387594223022461,
      "metric_transpile_time_s": 0.0,
      "execution_time_s": 0.013935089111328125,
      "n_circuits": 1,
      "circuit_depth": 227,
      "gate_counts": {
        "rz": 118,
        "sx": 94,
        "cx": 71,
        "measure": 4,
        "x": 1
      },
      "n_qubits": 5,
      "circuit_metrics_available": true,
      "circuit_metrics_from_segment": 0,
      "circuit_metrics_exact": false
    },
    {
      "shots": 150000,
      "n_kept": 149657,
      "p_success": 0.9977133333333333,
      "n_steps": 6,
      "step": 6,
      "segment_idx": 5,
      "segment_size": 1,
      "cumulative_norm": 2.186677074625697,
      "transpile": {
        "wall_time": 0.0339052677154541,
        "optimization_level": 1,
        "before": {
          "depth": 13,
          "num_qubits": 5,
          "gate_counts": {
            "measure": 4,
            "unitary": 3,
            "cry": 3,
            "ccry": 3,
            "qft": 1,
            "c3ry": 1,
            "qft_dg": 1
          }
        },
        "after": {
          "depth": 45,
          "num_qubits": 5,
          "gate_counts": {
            "cu": 16,
            "cx": 12,
            "h": 6,
            "cp": 6,
            "measure": 4,
            "unitary": 3,
            "cry": 3,
            "swap": 2
          }
        }
      },
      "execute": {
        "wall_time": 0.015366077423095703,
        "shots_requested": 150000,
        "shots_executed": 150000,
        "backend_time": 0.014141083
      },
      "circuit_construction_time_s": 0.0013399124145507812,
      "transpilation_time_s": 0.0339052677154541,
      "metric_transpile_time_s": 0.0,
      "execution_time_s": 0.015366077423095703,
      "n_circuits": 1,
      "circuit_depth": 227,
      "gate_counts": {
        "rz": 118,
        "sx": 94,
        "cx": 71,
        "measure": 4,
        "x": 1
      },
      "n_qubits": 5,
      "circuit_metrics_available": true,
      "circuit_metrics_from_segment": 0,
      "circuit_metrics_exact": false,
      "method_wall_time_s": 2.2299180030822754,
      "segments_full": [
        {
          "segment_idx": 0,
          "step": 1,
          "is_snapshot": true,
          "shots": 150000,
          "n_kept": 148881,
          "p_success": 0.99254,
          "cumulative_norm": 2.2084884172423176,
          "execution_time_s": 0.019430875778198242,
          "execute": {
            "wall_time": 0.019430875778198242,
            "shots_requested": 150000,
            "shots_executed": 150000,
            "backend_time": 0.01585
          },
          "circuit_depth": 227,
          "gate_counts": {
            "rz": 118,
            "sx": 94,
            "cx": 71,
            "measure": 4,
            "x": 1
          },
          "n_qubits": 5,
          "circuit_metrics_available": true,
          "circuit_metrics_from_segment": 0,
          "circuit_metrics_exact": true
        },
        {
          "segment_idx": 1,
          "step": 2,
          "is_snapshot": true,
          "shots": 150000,
          "n_kept": 149093,
          "p_success": 0.9939533333333334,
          "cumulative_norm": 2.2018012965694154,
          "execution_time_s": 0.014519929885864258,
          "execute": {
            "wall_time": 0.014519929885864258,
            "shots_requested": 150000,
            "shots_executed": 150000,
            "backend_time": 0.01332725
          },
          "circuit_depth": 227,
          "gate_counts": {
            "rz": 118,
            "sx": 94,
            "cx": 71,
            "measure": 4,
            "x": 1
          },
          "n_qubits": 5,
          "circuit_metrics_available": true,
          "circuit_metrics_from_segment": 0,
          "circuit_metrics_exact": false
        },
        {
          "segment_idx": 2,
          "step": 3,
          "is_snapshot": true,
          "shots": 150000,
          "n_kept": 149286,
          "p_success": 0.99524,
          "cumulative_norm": 2.196554758656106,
          "execution_time_s": 0.01493215560913086,
          "execute": {
            "wall_time": 0.01493215560913086,
            "shots_requested": 150000,
            "shots_executed": 150000,
            "backend_time": 0.013721
          },
          "circuit_depth": 227,
          "gate_counts": {
            "rz": 118,
            "sx": 94,
            "cx": 71,
            "measure": 4,
            "x": 1
          },
          "n_qubits": 5,
          "circuit_metrics_available": true,
          "circuit_metrics_from_segment": 0,
          "circuit_metrics_exact": false
        },
        {
          "segment_idx": 3,
          "step": 4,
          "is_snapshot": true,
          "shots": 150000,
          "n_kept": 149435,
          "p_success": 0.9962333333333333,
          "cumulative_norm": 2.1924140109778913,
          "execution_time_s": 0.014503955841064453,
          "execute": {
            "wall_time": 0.014503955841064453,
            "shots_requested": 150000,
            "shots_executed": 150000,
            "backend_time": 0.013326792
          },
          "circuit_depth": 227,
          "gate_counts": {
            "rz": 118,
            "sx": 94,
            "cx": 71,
            "measure": 4,
            "x": 1
          },
          "n_qubits": 5,
          "circuit_metrics_available": true,
          "circuit_metrics_from_segment": 0,
          "circuit_metrics_exact": false
        },
        {
          "segment_idx": 4,
          "step": 5,
          "is_snapshot": true,
          "shots": 150000,
          "n_kept": 149558,
          "p_success": 0.9970533333333333,
          "cumulative_norm": 2.189181471273985,
          "execution_time_s": 0.013935089111328125,
          "execute": {
            "wall_time": 0.013935089111328125,
            "shots_requested": 150000,
            "shots_executed": 150000,
            "backend_time": 0.012775833
          },
          "circuit_depth": 227,
          "gate_counts": {
            "rz": 118,
            "sx": 94,
            "cx": 71,
            "measure": 4,
            "x": 1
          },
          "n_qubits": 5,
          "circuit_metrics_available": true,
          "circuit_metrics_from_segment": 0,
          "circuit_metrics_exact": false
        },
        {
          "segment_idx": 5,
          "step": 6,
          "is_snapshot": true,
          "shots": 150000,
          "n_kept": 149657,
          "p_success": 0.9977133333333333,
          "cumulative_norm": 2.186677074625697,
          "execution_time_s": 0.015366077423095703,
          "execute": {
            "wall_time": 0.015366077423095703,
            "shots_requested": 150000,
            "shots_executed": 150000,
            "backend_time": 0.014141083
          },
          "circuit_depth": 227,
          "gate_counts": {
            "rz": 118,
            "sx": 94,
            "cx": 71,
            "measure": 4,
            "x": 1
          },
          "n_qubits": 5,
          "circuit_metrics_available": true,
          "circuit_metrics_from_segment": 0,
          "circuit_metrics_exact": false
        }
      ]
    }
  ],
  "_source": "solver"
}