{
  "_source": "sweep",
  "directory": "/Users/agallojr/q8020/2026-06-14/_0a52e9ab/28a857e1",
  "files": [
    {
      "name": "q8020_params_28a857e1.json",
      "path": "q8020_params_28a857e1.json",
      "size_bytes": 1799,
      "modified": "2026-06-15T01:26:25.579988Z",
      "type": "json"
    },
    {
      "name": "q8020_stdout_28a857e1.txt",
      "path": "q8020_stdout_28a857e1.txt",
      "size_bytes": 671,
      "modified": "2026-06-15T01:26:36.078933Z",
      "type": "txt"
    },
    {
      "name": "q8020_stderr_28a857e1.txt",
      "path": "q8020_stderr_28a857e1.txt",
      "size_bytes": 369,
      "modified": "2026-06-15T01:26:36.078478Z",
      "type": "txt"
    },
    {
      "name": "q8020_artifacts_0.json",
      "path": "q8020_artifacts_0.json",
      "size_bytes": 2074,
      "modified": "2026-06-15T01:26:35.894143Z",
      "type": "json"
    },
    {
      "name": "q8020_case_0.json",
      "path": "q8020_case_0.json",
      "size_bytes": 728,
      "modified": "2026-06-15T01:26:35.877982Z",
      "type": "json"
    },
    {
      "name": "q8020_analysis_0.json",
      "path": "q8020_analysis_0.json",
      "size_bytes": 2619,
      "modified": "2026-06-15T01:26:35.893829Z",
      "type": "json"
    },
    {
      "name": "q8020_env_before_28a857e1.json",
      "path": "q8020_env_before_28a857e1.json",
      "size_bytes": 3002,
      "modified": "2026-06-15T01:26:25.579597Z",
      "type": "json"
    },
    {
      "name": "q8020_results_0.json",
      "path": "q8020_results_0.json",
      "size_bytes": 955,
      "modified": "2026-06-15T01:26:35.878325Z",
      "type": "json"
    }
  ]
}