{
  "transpile_passes": [
    {
      "step": 0,
      "wall_time_generate_s": 8.175416,
      "wall_time_transpile_s": 1.654466,
      "wall_time_execute_s": 1.963582,
      "before": {
        "depth": 5,
        "num_qubits": 14,
        "gate_count": 19
      },
      "after": {
        "depth": 22395,
        "num_qubits": 14,
        "gate_count": 22499
      }
    },
    {
      "step": 1,
      "wall_time_generate_s": 7.284066,
      "wall_time_transpile_s": 1.500981,
      "wall_time_execute_s": 1.408044,
      "before": {
        "depth": 5,
        "num_qubits": 13,
        "gate_count": 18
      },
      "after": {
        "depth": 19310,
        "num_qubits": 13,
        "gate_count": 19395
      }
    },
    {
      "step": 2,
      "wall_time_generate_s": 7.480429,
      "wall_time_transpile_s": 1.479407,
      "wall_time_execute_s": 1.419921,
      "before": {
        "depth": 5,
        "num_qubits": 13,
        "gate_count": 18
      },
      "after": {
        "depth": 19316,
        "num_qubits": 13,
        "gate_count": 19401
      }
    },
    {
      "step": 3,
      "wall_time_generate_s": 8.677505,
      "wall_time_transpile_s": 1.73058,
      "wall_time_execute_s": 1.966734,
      "before": {
        "depth": 5,
        "num_qubits": 14,
        "gate_count": 19
      },
      "after": {
        "depth": 22389,
        "num_qubits": 14,
        "gate_count": 22493
      }
    },
    {
      "step": 4,
      "wall_time_generate_s": 8.702894,
      "wall_time_transpile_s": 1.662561,
      "wall_time_execute_s": 1.968208,
      "before": {
        "depth": 5,
        "num_qubits": 14,
        "gate_count": 19
      },
      "after": {
        "depth": 22397,
        "num_qubits": 14,
        "gate_count": 22501
      }
    },
    {
      "step": 5,
      "wall_time_generate_s": 8.622295,
      "wall_time_transpile_s": 1.712324,
      "wall_time_execute_s": 1.952174,
      "before": {
        "depth": 5,
        "num_qubits": 14,
        "gate_count": 19
      },
      "after": {
        "depth": 22397,
        "num_qubits": 14,
        "gate_count": 22501
      }
    },
    {
      "step": 6,
      "wall_time_generate_s": 8.976118,
      "wall_time_transpile_s": 1.637355,
      "wall_time_execute_s": 1.942417,
      "before": {
        "depth": 5,
        "num_qubits": 14,
        "gate_count": 19
      },
      "after": {
        "depth": 22391,
        "num_qubits": 14,
        "gate_count": 22495
      }
    },
    {
      "step": 7,
      "wall_time_generate_s": 8.53326,
      "wall_time_transpile_s": 1.942542,
      "wall_time_execute_s": 1.922832,
      "before": {
        "depth": 5,
        "num_qubits": 14,
        "gate_count": 19
      },
      "after": {
        "depth": 22395,
        "num_qubits": 14,
        "gate_count": 22499
      }
    },
    {
      "step": 8,
      "wall_time_generate_s": 8.520696,
      "wall_time_transpile_s": 1.964516,
      "wall_time_execute_s": 1.933815,
      "before": {
        "depth": 5,
        "num_qubits": 14,
        "gate_count": 19
      },
      "after": {
        "depth": 22395,
        "num_qubits": 14,
        "gate_count": 22499
      }
    },
    {
      "step": 9,
      "wall_time_generate_s": 8.65668,
      "wall_time_transpile_s": 1.68187,
      "wall_time_execute_s": 1.909144,
      "before": {
        "depth": 5,
        "num_qubits": 14,
        "gate_count": 19
      },
      "after": {
        "depth": 22393,
        "num_qubits": 14,
        "gate_count": 22497
      }
    },
    {
      "step": 10,
      "wall_time_generate_s": 8.722243,
      "wall_time_transpile_s": 1.702264,
      "wall_time_execute_s": 1.931612,
      "before": {
        "depth": 5,
        "num_qubits": 14,
        "gate_count": 19
      },
      "after": {
        "depth": 22395,
        "num_qubits": 14,
        "gate_count": 22499
      }
    },
    {
      "step": 11,
      "wall_time_generate_s": 8.913321,
      "wall_time_transpile_s": 1.670235,
      "wall_time_execute_s": 1.918132,
      "before": {
        "depth": 5,
        "num_qubits": 14,
        "gate_count": 19
      },
      "after": {
        "depth": 22395,
        "num_qubits": 14,
        "gate_count": 22499
      }
    },
    {
      "step": 12,
      "wall_time_generate_s": 8.807147,
      "wall_time_transpile_s": 1.664381,
      "wall_time_execute_s": 1.9011,
      "before": {
        "depth": 5,
        "num_qubits": 14,
        "gate_count": 19
      },
      "after": {
        "depth": 22390,
        "num_qubits": 14,
        "gate_count": 22494
      }
    },
    {
      "step": 13,
      "wall_time_generate_s": 8.739052,
      "wall_time_transpile_s": 1.720207,
      "wall_time_execute_s": 1.900568,
      "before": {
        "depth": 5,
        "num_qubits": 14,
        "gate_count": 19
      },
      "after": {
        "depth": 22391,
        "num_qubits": 14,
        "gate_count": 22495
      }
    },
    {
      "step": 14,
      "wall_time_generate_s": 8.912225,
      "wall_time_transpile_s": 1.665613,
      "wall_time_execute_s": 1.870317,
      "before": {
        "depth": 5,
        "num_qubits": 14,
        "gate_count": 19
      },
      "after": {
        "depth": 22393,
        "num_qubits": 14,
        "gate_count": 22497
      }
    }
  ],
  "circuit_timing_total_s": {
    "generate": 127.723347,
    "transpile": 25.3893,
    "execute": 27.908602,
    "total": 181.021249
  },
  "linear_system": {
    "matrix_size_original": 15,
    "matrix_size_padded": 16,
    "matrix_size_hermitian": 32,
    "condition_number_range": [
      50.8441,
      95.9779
    ]
  },
  "file_inventory": {
    "qpy_generated": [],
    "qpy_transpiled": [],
    "csv": [
      {
        "name": "dq_nelem5_iter0_statevector_shots5000.csv",
        "size_bytes": 548,
        "modified": "2026-03-01T21:36:10.928866Z"
      },
      {
        "name": "dq_nelem5_iter10_statevector_shots5000.csv",
        "size_bytes": 564,
        "modified": "2026-03-01T21:36:10.930861Z"
      },
      {
        "name": "dq_nelem5_iter11_statevector_shots5000.csv",
        "size_bytes": 552,
        "modified": "2026-03-01T21:36:10.932860Z"
      },
      {
        "name": "dq_nelem5_iter12_statevector_shots5000.csv",
        "size_bytes": 572,
        "modified": "2026-03-01T21:36:10.933874Z"
      },
      {
        "name": "dq_nelem5_iter13_statevector_shots5000.csv",
        "size_bytes": 502,
        "modified": "2026-03-01T21:36:10.935873Z"
      },
      {
        "name": "dq_nelem5_iter14_statevector_shots5000.csv",
        "size_bytes": 520,
        "modified": "2026-03-01T21:36:10.937866Z"
      },
      {
        "name": "dq_nelem5_iter1_statevector_shots5000.csv",
        "size_bytes": 561,
        "modified": "2026-03-01T21:36:10.939863Z"
      },
      {
        "name": "dq_nelem5_iter2_statevector_shots5000.csv",
        "size_bytes": 459,
        "modified": "2026-03-01T21:36:10.941865Z"
      },
      {
        "name": "dq_nelem5_iter3_statevector_shots5000.csv",
        "size_bytes": 424,
        "modified": "2026-03-01T21:36:10.942877Z"
      },
      {
        "name": "dq_nelem5_iter4_statevector_shots5000.csv",
        "size_bytes": 436,
        "modified": "2026-03-01T21:36:10.944870Z"
      },
      {
        "name": "dq_nelem5_iter5_statevector_shots5000.csv",
        "size_bytes": 573,
        "modified": "2026-03-01T21:36:10.946866Z"
      },
      {
        "name": "dq_nelem5_iter6_statevector_shots5000.csv",
        "size_bytes": 462,
        "modified": "2026-03-01T21:36:10.948865Z"
      },
      {
        "name": "dq_nelem5_iter7_statevector_shots5000.csv",
        "size_bytes": 513,
        "modified": "2026-03-01T21:36:10.950860Z"
      },
      {
        "name": "dq_nelem5_iter8_statevector_shots5000.csv",
        "size_bytes": 515,
        "modified": "2026-03-01T21:36:10.951874Z"
      },
      {
        "name": "dq_nelem5_iter9_statevector_shots5000.csv",
        "size_bytes": 494,
        "modified": "2026-03-01T21:36:10.953871Z"
      },
      {
        "name": "final_results_nelem5_HHL_statevector_nshots5000.csv",
        "size_bytes": 419,
        "modified": "2026-03-01T21:36:10.955867Z"
      },
      {
        "name": "hhl_metrics_nelem5_statevector_shots5000.csv",
        "size_bytes": 1694,
        "modified": "2026-03-01T21:36:10.957864Z"
      },
      {
        "name": "qc_metadata_nelem5_statevector_shots5000.csv",
        "size_bytes": 3490,
        "modified": "2026-03-01T21:36:10.961864Z"
      },
      {
        "name": "residual_nelem5_HHL_statevector_nshots5000.csv",
        "size_bytes": 1285,
        "modified": "2026-03-01T21:36:10.963861Z"
      },
      {
        "name": "results_nelem5_HHL_statevector_nshots5000_iter0.csv",
        "size_bytes": 344,
        "modified": "2026-03-01T21:36:10.964878Z"
      },
      {
        "name": "results_nelem5_HHL_statevector_nshots5000_iter1.csv",
        "size_bytes": 373,
        "modified": "2026-03-01T21:36:10.966872Z"
      },
      {
        "name": "results_nelem5_HHL_statevector_nshots5000_iter10.csv",
        "size_bytes": 418,
        "modified": "2026-03-01T21:36:10.968872Z"
      },
      {
        "name": "results_nelem5_HHL_statevector_nshots5000_iter11.csv",
        "size_bytes": 419,
        "modified": "2026-03-01T21:36:10.970872Z"
      },
      {
        "name": "results_nelem5_HHL_statevector_nshots5000_iter12.csv",
        "size_bytes": 420,
        "modified": "2026-03-01T21:36:10.972871Z"
      },
      {
        "name": "results_nelem5_HHL_statevector_nshots5000_iter13.csv",
        "size_bytes": 418,
        "modified": "2026-03-01T21:36:10.974868Z"
      },
      {
        "name": "results_nelem5_HHL_statevector_nshots5000_iter14.csv",
        "size_bytes": 419,
        "modified": "2026-03-01T21:36:10.976867Z"
      },
      {
        "name": "results_nelem5_HHL_statevector_nshots5000_iter2.csv",
        "size_bytes": 372,
        "modified": "2026-03-01T21:36:10.978862Z"
      },
      {
        "name": "results_nelem5_HHL_statevector_nshots5000_iter3.csv",
        "size_bytes": 375,
        "modified": "2026-03-01T21:36:10.980862Z"
      },
      {
        "name": "results_nelem5_HHL_statevector_nshots5000_iter4.csv",
        "size_bytes": 375,
        "modified": "2026-03-01T21:36:10.982860Z"
      },
      {
        "name": "results_nelem5_HHL_statevector_nshots5000_iter5.csv",
        "size_bytes": 370,
        "modified": "2026-03-01T21:36:10.983874Z"
      },
      {
        "name": "results_nelem5_HHL_statevector_nshots5000_iter6.csv",
        "size_bytes": 419,
        "modified": "2026-03-01T21:36:10.985871Z"
      },
      {
        "name": "results_nelem5_HHL_statevector_nshots5000_iter7.csv",
        "size_bytes": 422,
        "modified": "2026-03-01T21:36:10.987863Z"
      },
      {
        "name": "results_nelem5_HHL_statevector_nshots5000_iter8.csv",
        "size_bytes": 418,
        "modified": "2026-03-01T21:36:10.989862Z"
      },
      {
        "name": "results_nelem5_HHL_statevector_nshots5000_iter9.csv",
        "size_bytes": 420,
        "modified": "2026-03-01T21:36:10.990878Z"
      },
      {
        "name": "results_nelem5_iter0_statevector_shots5000.csv",
        "size_bytes": 344,
        "modified": "2026-03-01T21:36:10.992874Z"
      },
      {
        "name": "results_nelem5_iter10_statevector_shots5000.csv",
        "size_bytes": 418,
        "modified": "2026-03-01T21:36:10.994869Z"
      },
      {
        "name": "results_nelem5_iter11_statevector_shots5000.csv",
        "size_bytes": 419,
        "modified": "2026-03-01T21:36:10.996870Z"
      },
      {
        "name": "results_nelem5_iter12_statevector_shots5000.csv",
        "size_bytes": 420,
        "modified": "2026-03-01T21:36:10.998864Z"
      },
      {
        "name": "results_nelem5_iter13_statevector_shots5000.csv",
        "size_bytes": 418,
        "modified": "2026-03-01T21:36:11.000860Z"
      },
      {
        "name": "results_nelem5_iter14_statevector_shots5000.csv",
        "size_bytes": 419,
        "modified": "2026-03-01T21:36:11.002868Z"
      },
      {
        "name": "results_nelem5_iter1_statevector_shots5000.csv",
        "size_bytes": 373,
        "modified": "2026-03-01T21:36:11.003896Z"
      },
      {
        "name": "results_nelem5_iter2_statevector_shots5000.csv",
        "size_bytes": 372,
        "modified": "2026-03-01T21:36:11.005892Z"
      },
      {
        "name": "results_nelem5_iter3_statevector_shots5000.csv",
        "size_bytes": 375,
        "modified": "2026-03-01T21:36:11.007888Z"
      },
      {
        "name": "results_nelem5_iter4_statevector_shots5000.csv",
        "size_bytes": 375,
        "modified": "2026-03-01T21:36:11.009886Z"
      },
      {
        "name": "results_nelem5_iter5_statevector_shots5000.csv",
        "size_bytes": 370,
        "modified": "2026-03-01T21:36:11.011876Z"
      },
      {
        "name": "results_nelem5_iter6_statevector_shots5000.csv",
        "size_bytes": 419,
        "modified": "2026-03-01T21:36:11.013867Z"
      },
      {
        "name": "results_nelem5_iter7_statevector_shots5000.csv",
        "size_bytes": 422,
        "modified": "2026-03-01T21:36:11.015868Z"
      },
      {
        "name": "results_nelem5_iter8_statevector_shots5000.csv",
        "size_bytes": 418,
        "modified": "2026-03-01T21:36:11.017866Z"
      },
      {
        "name": "results_nelem5_iter9_statevector_shots5000.csv",
        "size_bytes": 420,
        "modified": "2026-03-01T21:36:11.018876Z"
      }
    ],
    "pkl": [
      {
        "name": "metadata_nelem5_HHL_statevector_nshots5000.pkl",
        "size_bytes": 616,
        "modified": "2026-03-01T21:36:10.959864Z"
      },
      {
        "name": "system_Ab_nelem5_iter0.pkl",
        "size_bytes": 2115,
        "modified": "2026-03-01T21:36:11.027859Z"
      },
      {
        "name": "system_Ab_nelem5_iter1.pkl",
        "size_bytes": 2115,
        "modified": "2026-03-01T21:36:11.029859Z"
      },
      {
        "name": "system_Ab_nelem5_iter10.pkl",
        "size_bytes": 2115,
        "modified": "2026-03-01T21:36:11.031860Z"
      },
      {
        "name": "system_Ab_nelem5_iter11.pkl",
        "size_bytes": 2115,
        "modified": "2026-03-01T21:36:11.033859Z"
      },
      {
        "name": "system_Ab_nelem5_iter12.pkl",
        "size_bytes": 2115,
        "modified": "2026-03-01T21:36:11.035862Z"
      },
      {
        "name": "system_Ab_nelem5_iter13.pkl",
        "size_bytes": 2115,
        "modified": "2026-03-01T21:36:11.037859Z"
      },
      {
        "name": "system_Ab_nelem5_iter14.pkl",
        "size_bytes": 2115,
        "modified": "2026-03-01T21:36:11.039859Z"
      },
      {
        "name": "system_Ab_nelem5_iter2.pkl",
        "size_bytes": 2115,
        "modified": "2026-03-01T21:36:11.041864Z"
      },
      {
        "name": "system_Ab_nelem5_iter3.pkl",
        "size_bytes": 2115,
        "modified": "2026-03-01T21:36:11.043864Z"
      },
      {
        "name": "system_Ab_nelem5_iter4.pkl",
        "size_bytes": 2115,
        "modified": "2026-03-01T21:36:11.045870Z"
      },
      {
        "name": "system_Ab_nelem5_iter5.pkl",
        "size_bytes": 2115,
        "modified": "2026-03-01T21:36:11.047870Z"
      },
      {
        "name": "system_Ab_nelem5_iter6.pkl",
        "size_bytes": 2115,
        "modified": "2026-03-01T21:36:11.049875Z"
      },
      {
        "name": "system_Ab_nelem5_iter7.pkl",
        "size_bytes": 2115,
        "modified": "2026-03-01T21:36:11.051876Z"
      },
      {
        "name": "system_Ab_nelem5_iter8.pkl",
        "size_bytes": 2115,
        "modified": "2026-03-01T21:36:11.053875Z"
      },
      {
        "name": "system_Ab_nelem5_iter9.pkl",
        "size_bytes": 2115,
        "modified": "2026-03-01T21:36:11.055860Z"
      }
    ],
    "png": [
      {
        "name": "solution_plot_nelem5_HHL_statevector_nshots5000.png",
        "size_bytes": 166150,
        "modified": "2026-03-01T21:36:11.024882Z"
      }
    ],
    "other": [
      {
        "name": "run.log",
        "size_bytes": 54104,
        "modified": "2026-03-01T21:36:11.021866Z"
      }
    ]
  },
  "_source": "solver"
}